AUTHORS
LICENSE
MANIFEST.in
README.md
setup.py
colmena_zeromq_pyre.egg-info/PKG-INFO
colmena_zeromq_pyre.egg-info/SOURCES.txt
colmena_zeromq_pyre.egg-info/dependency_links.txt
colmena_zeromq_pyre.egg-info/requires.txt
colmena_zeromq_pyre.egg-info/top_level.txt
pyre/__init__.py
pyre/pyre.py
pyre/pyre_event.py
pyre/pyre_group.py
pyre/pyre_node.py
pyre/pyre_peer.py
pyre/zactor.py
pyre/zbeacon.py
pyre/zhelper.py
pyre/zre_msg.py
pyre/zsocket.py
tests/test_network_disconnect.py
tests/test_pyre.py
tests/test_zactor.py
tests/test_zbeacon.py
tests/test_zhelper.py